{
  "puzzle": {
    "puzzle_id": 2856,
    "date": "March 4, 2026",
    "letters": "G",
    "all_letters": "GCEFINT",
    "word_count": 37,
    "pangrams_count": 2
  },
  "words": [
    {
      "word": "effecting",
      "is_pangram": 1,
      "length": 9
    },
    {
      "word": "infecting",
      "is_pangram": 1,
      "length": 9
    },
    {
      "word": "enticing",
      "is_pangram": 0,
      "length": 8
    },
    {
      "word": "feigning",
      "is_pangram": 0,
      "length": 8
    },
    {
      "word": "feinting",
      "is_pangram": 0,
      "length": 8
    },
    {
      "word": "igniting",
      "is_pangram": 0,
      "length": 8
    },
    {
      "word": "inciting",
      "is_pangram": 0,
      "length": 8
    },
    {
      "word": "tingeing",
      "is_pangram": 0,
      "length": 8
    },
    {
      "word": "fencing",
      "is_pangram": 0,
      "length": 7
    },
    {
      "word": "fitting",
      "is_pangram": 0,
      "length": 7
    },
    {
      "word": "genetic",
      "is_pangram": 0,
      "length": 7
    },
    {
      "word": "getting",
      "is_pangram": 0,
      "length": 7
    },
    {
      "word": "gifting",
      "is_pangram": 0,
      "length": 7
    },
    {
      "word": "gigging",
      "is_pangram": 0,
      "length": 7
    },
    {
      "word": "ginning",
      "is_pangram": 0,
      "length": 7
    },
    {
      "word": "netting",
      "is_pangram": 0,
      "length": 7
    },
    {
      "word": "tenting",
      "is_pangram": 0,
      "length": 7
    },
    {
      "word": "tinging",
      "is_pangram": 0,
      "length": 7
    },
    {
      "word": "tinning",
      "is_pangram": 0,
      "length": 7
    },
    {
      "word": "tinting",
      "is_pangram": 0,
      "length": 7
    },
    {
      "word": "citing",
      "is_pangram": 0,
      "length": 6
    },
    {
      "word": "egging",
      "is_pangram": 0,
      "length": 6
    },
    {
      "word": "engine",
      "is_pangram": 0,
      "length": 6
    },
    {
      "word": "feting",
      "is_pangram": 0,
      "length": 6
    },
    {
      "word": "fifing",
      "is_pangram": 0,
      "length": 6
    },
    {
      "word": "fining",
      "is_pangram": 0,
      "length": 6
    },
    {
      "word": "ignite",
      "is_pangram": 0,
      "length": 6
    },
    {
      "word": "inning",
      "is_pangram": 0,
      "length": 6
    },
    {
      "word": "teeing",
      "is_pangram": 0,
      "length": 6
    },
    {
      "word": "feign",
      "is_pangram": 0,
      "length": 5
    },
    {
      "word": "genie",
      "is_pangram": 0,
      "length": 5
    },
    {
      "word": "genii",
      "is_pangram": 0,
      "length": 5
    },
    {
      "word": "icing",
      "is_pangram": 0,
      "length": 5
    },
    {
      "word": "tinge",
      "is_pangram": 0,
      "length": 5
    },
    {
      "word": "gene",
      "is_pangram": 0,
      "length": 4
    },
    {
      "word": "gent",
      "is_pangram": 0,
      "length": 4
    },
    {
      "word": "gift",
      "is_pangram": 0,
      "length": 4
    }
  ],
  "totalPoints": 246,
  "hasPerfectPangram": false,
  "perfectPangrams": []
}